filechooser/__init__.py
filechooser/main.py
filechooser/parse_commandline.py
filechooser-0.1.6.data/scripts/autorotate.sh
tests/__init__.py
filechooser-0.1.6.dist-info/METADATA
filechooser-0.1.6.dist-info/WHEEL
filechooser-0.1.6.dist-info/entry_points.txt
filechooser-0.1.6.dist-info/top_level.txt
filechooser-0.1.6.dist-info/RECORD
