Metadata-Version: 2.1
Name: filechooser
Version: 0.1.6
Summary: A script that copies a random selection of files from a set of folders to a single destination folder
Home-page: https://github.com/nicolasbock/filechooser.git
Author: Nicolas Bock
Author-email: nicolasbock@gmail.com
License: BSD
Platform: UNKNOWN
